odoo/addons/purchase_sign/README.rst
odoo/addons/purchase_sign/__init__.py
odoo/addons/purchase_sign/__manifest__.py
odoo/addons/purchase_sign/controllers/__init__.py
odoo/addons/purchase_sign/controllers/main.py
odoo/addons/purchase_sign/i18n/it.po
odoo/addons/purchase_sign/i18n/purchase_sign.pot
odoo/addons/purchase_sign/models/__init__.py
odoo/addons/purchase_sign/models/purchase_order.py
odoo/addons/purchase_sign/models/res_company.py
odoo/addons/purchase_sign/models/res_config_settings.py
odoo/addons/purchase_sign/readme/CONTRIBUTORS.rst
odoo/addons/purchase_sign/readme/DESCRIPTION.rst
odoo/addons/purchase_sign/report/purchase_order_template.xml
odoo/addons/purchase_sign/static/description/icon.png
odoo/addons/purchase_sign/static/description/index.html
odoo/addons/purchase_sign/static/tests/tours/purchase_signature.esm.js
odoo/addons/purchase_sign/templates/purchase_portal_templates.xml
odoo/addons/purchase_sign/tests/__init__.py
odoo/addons/purchase_sign/tests/test_purchase_sign.py
odoo/addons/purchase_sign/views/purchase_view.xml
odoo/addons/purchase_sign/views/res_config_settings_view.xml
odoo_addon_purchase_sign-16.0.1.0.0.4.dist-info/METADATA
odoo_addon_purchase_sign-16.0.1.0.0.4.dist-info/WHEEL
odoo_addon_purchase_sign-16.0.1.0.0.4.dist-info/top_level.txt
odoo_addon_purchase_sign-16.0.1.0.0.4.dist-info/RECORD
